moneykit/__init__.py
moneykit/base_client.py
moneykit/client.py
moneykit/core/__init__.py
moneykit/core/api_error.py
moneykit/core/client_wrapper.py
moneykit/core/datetime_utils.py
moneykit/core/jsonable_encoder.py
moneykit/core/remove_none_from_headers.py
moneykit/environment.py
moneykit/errors/__init__.py
moneykit/errors/bad_request_error.py
moneykit/errors/forbidden_error.py
moneykit/errors/not_found_error.py
moneykit/errors/too_many_requests_error.py
moneykit/errors/unauthorized_error.py
moneykit/errors/unprocessable_entity_error.py
moneykit/py.typed
moneykit/resources/__init__.py
moneykit/resources/access_token/__init__.py
moneykit/resources/access_token/client.py
moneykit/resources/accounts/__init__.py
moneykit/resources/accounts/client.py
moneykit/resources/identity/__init__.py
moneykit/resources/identity/client.py
moneykit/resources/institutions/__init__.py
moneykit/resources/institutions/client.py
moneykit/resources/link_session/__init__.py
moneykit/resources/link_session/client.py
moneykit/resources/links/__init__.py
moneykit/resources/links/client.py
moneykit/resources/products/__init__.py
moneykit/resources/products/client.py
moneykit/resources/transactions/__init__.py
moneykit/resources/transactions/client.py
moneykit/types/__init__.py
moneykit/types/account.py
moneykit/types/account_balances.py
moneykit/types/account_group.py
moneykit/types/account_identity.py
moneykit/types/account_numbers.py
moneykit/types/account_numbers_link_product.py
moneykit/types/account_numbers_product_settings.py
moneykit/types/account_type.py
moneykit/types/account_with_account_numbers.py
moneykit/types/accounts_link_product.py
moneykit/types/ach_number.py
moneykit/types/address.py
moneykit/types/api_error_auth_expired_access_token_response.py
moneykit/types/api_error_auth_unauthorized_response.py
moneykit/types/api_error_rate_limit_exceeded_response.py
moneykit/types/bacs_number.py
moneykit/types/basic_account_details.py
fern_moneykit-0.0.12.dist-info/METADATA
fern_moneykit-0.0.12.dist-info/WHEEL
fern_moneykit-0.0.12.dist-info/RECORD
